dojahcore/__init__.py
dojahcore/_app.py
dojahcore/core.py
dojahcore/dojah.py
dojahcore/financial.py
dojahcore/general.py
dojahcore/identification.py
dojahcore/messaging.py
dojahcore/server_error.py
dojahcore/verification.py
dojahcore/wallet.py
dojahcore-0.0.5.dist-info/LICENCE
dojahcore-0.0.5.dist-info/METADATA
dojahcore-0.0.5.dist-info/WHEEL
dojahcore-0.0.5.dist-info/top_level.txt
dojahcore-0.0.5.dist-info/RECORD
