Metadata-Version: 2.1
Name: dojahcore
Version: 0.0.5
Summary: The official Dojah Core Python package
Home-page: UNKNOWN
Author: Dojah
Author-email: taiwo@dojah.io
License: UNKNOWN
Keywords: python,dojah,kyc,verification
Platform: UNKNOWN
Classifier: Programming Language :: Python :: 3
Classifier: Operating System :: OS Independent
Requires-Dist: requests
Requires-Dist: python-dotenv
